neural_network/__init__.py
neural_network/nn/__init__.py
neural_network/nn/core.py
neural_network/utils/__init__.py
neural_network/utils/utillties.py
vicNeuralNetwork-0.0.2.dist-info/LICENSE
vicNeuralNetwork-0.0.2.dist-info/METADATA
vicNeuralNetwork-0.0.2.dist-info/WHEEL
vicNeuralNetwork-0.0.2.dist-info/top_level.txt
vicNeuralNetwork-0.0.2.dist-info/RECORD
